sphinx_apischema/__init__.py
sphinx_apischema/_version_git.py
sphinx_apischema/example.py
sphinx_apischema-0.1.dist-info/LICENSE
sphinx_apischema-0.1.dist-info/METADATA
sphinx_apischema-0.1.dist-info/WHEEL
sphinx_apischema-0.1.dist-info/top_level.txt
sphinx_apischema-0.1.dist-info/RECORD
