Metadata-Version: 2.1
Name: sphinx-apischema
Version: 0.1
Summary: Sphinx extension to autodoc for apischema annotated classes/functions
Home-page: https://github.com/dls-controls/sphinx-apischema
Author: Tom Cobb
Author-email: tom.cobb@diamond.ac.uk
License: Apache License 2.0
Platform: UNKNOWN
Classifier: Development Status :: 4 - Beta
Classifier: License :: OSI Approved :: Apache Software License
Classifier: Programming Language :: Python :: 3.7
Classifier: Programming Language :: Python :: 3.8
Classifier: Programming Language :: Python :: 3.9
Requires-Dist: sphinx (>=2.4)
Requires-Dist: apischema (>=0.15)
Requires-Dist: typing-extensions
